StreamV/Stream_Capture.py
StreamV/__init__.py
StreamV-0.0.3.dist-info/LICENSE
StreamV-0.0.3.dist-info/METADATA
StreamV-0.0.3.dist-info/WHEEL
StreamV-0.0.3.dist-info/top_level.txt
StreamV-0.0.3.dist-info/RECORD
