Metadata-Version: 2.1
Name: StreamV
Version: 0.0.3
Summary: Stream Capture with UDP
Home-page: UNKNOWN
Author: YanggeLiu
Author-email: liu1251658965@outlook.com
License: UNKNOWN
Platform: UNKNOWN
Classifier: Programming Language :: Python :: 3
Classifier: License :: OSI Approved :: MIT License
Classifier: Operating System :: OS Independent
Requires-Python: >=3.6
